znvis/__init__.py
znvis/mesh/__init__.py
znvis/mesh/custom.py
znvis/mesh/cylinder.py
znvis/mesh/mesh.py
znvis/mesh/sphere.py
znvis/particle/__init__.py
znvis/particle/particle.py
znvis/testing/__init__.py
znvis/testing/znvis_process.py
znvis/transformations/__init__.py
znvis/transformations/rotation_matrices.py
znvis/visualizer/__init__.py
znvis/visualizer/visualizer.py
ZnVis-0.1.0.dist-info/LICENSE
ZnVis-0.1.0.dist-info/METADATA
ZnVis-0.1.0.dist-info/WHEEL
ZnVis-0.1.0.dist-info/top_level.txt
ZnVis-0.1.0.dist-info/RECORD
