Metadata-Version: 2.1
Name: ZnVis
Version: 0.1.0
Summary: Visualization of particle trajectories.
Home-page: https://github.com/zincware/ZnVis
Author: zincwarecode
Author-email: tovey.samuel@gmail.com
Classifier: Programming Language :: Python :: 3
Classifier: License :: OSI Approved :: Eclipse Public License 2.0 (EPL-2.0)
Classifier: Operating System :: OS Independent
Requires-Python: >=3.8
License-File: LICENSE
Requires-Dist: open3d
Requires-Dist: numpy
Requires-Dist: pytest
Requires-Dist: rich
